gtklara/__init__.py
gtklara/fragments/__init__.py
gtklara/fragments/bool.py
gtklara/fragments/button.glade
gtklara/fragments/button.py
gtklara/fragments/combo_box.glade
gtklara/fragments/combo_box.py
gtklara/fragments/container.glade
gtklara/fragments/container.py
gtklara/fragments/doublec.py
gtklara/fragments/entry.glade
gtklara/fragments/entry.py
gtklara/fragments/label.glade
gtklara/fragments/label.py
gtklara/fragments/radio.glade
gtklara/fragments/radio.py
gtklara/state.py
gtklara/widgets.py
gtklara-0.0.15.dist-info/LICENSE
gtklara-0.0.15.dist-info/METADATA
gtklara-0.0.15.dist-info/WHEEL
gtklara-0.0.15.dist-info/RECORD
